<?xml version="1.0" encoding="UTF-8"?><?xml-stylesheet type='text/xsl' href='_UpgradeReport_Files/UpgradeReport.xslt'?><UpgradeLog>
<Properties><Property Name="Solution" Value="MP3 Scheduler">
</Property><Property Name="Solution File" Value="F:\ELECTRONIC\2015\Projects\32. Mas Automated mp3 playing system\PC interface\BackUp\V15.1.5.4\MP3 Scheduler\MP3 Scheduler.sln">
</Property><Property Name="User Options File" Value="F:\ELECTRONIC\2015\Projects\32. Mas Automated mp3 playing system\PC interface\BackUp\V15.1.5.4\MP3 Scheduler\MP3 Scheduler.suo">
</Property><Property Name="Date" Value="Friday, October 9, 2015">
</Property><Property Name="Time" Value="19:50 PM">
</Property></Properties><Event ErrorLevel="0" Project="" Source="MP3 Scheduler.sln" Description="File successfully backed up as F:\ELECTRONIC\2015\Projects\32. Mas Automated mp3 playing system\PC interface\BackUp\V15.1.5.4\MP3 Scheduler\Backup\MP3 Scheduler.sln">
</Event><Event ErrorLevel="0" Project="" Source="MP3 Scheduler.suo" Description="File successfully backed up as F:\ELECTRONIC\2015\Projects\32. Mas Automated mp3 playing system\PC interface\BackUp\V15.1.5.4\MP3 Scheduler\Backup\MP3 Scheduler.suo">
</Event><Event ErrorLevel="0" Project="MP3 Scheduler" Source="MP3 Scheduler\MP3 Scheduler.vbproj" Description="Project file successfully backed up as F:\ELECTRONIC\2015\Projects\32. Mas Automated mp3 playing system\PC interface\BackUp\V15.1.5.4\MP3 Scheduler\Backup\MP3 Scheduler\MP3 Scheduler.vbproj">
</Event><Event ErrorLevel="0" Project="MP3 Scheduler" Source="MP3 Scheduler\MP3 Scheduler.vbproj.user" Description="Project user file successfully backed up as F:\ELECTRONIC\2015\Projects\32. Mas Automated mp3 playing system\PC interface\BackUp\V15.1.5.4\MP3 Scheduler\Backup\MP3 Scheduler\MP3 Scheduler.vbproj.user">
</Event><Event ErrorLevel="0" Project="MP3 Scheduler" Source="MP3 Scheduler\ApplicationEvents.vb" Description="File successfully backed up as F:\ELECTRONIC\2015\Projects\32. Mas Automated mp3 playing system\PC interface\BackUp\V15.1.5.4\MP3 Scheduler\Backup\MP3 Scheduler\ApplicationEvents.vb">
</Event><Event ErrorLevel="0" Project="MP3 Scheduler" Source="MP3 Scheduler\Events.vb" Description="File successfully backed up as F:\ELECTRONIC\2015\Projects\32. Mas Automated mp3 playing system\PC interface\BackUp\V15.1.5.4\MP3 Scheduler\Backup\MP3 Scheduler\Events.vb">
</Event><Event ErrorLevel="0" Project="MP3 Scheduler" Source="MP3 Scheduler\New Event.Designer.vb" Description="File successfully backed up as F:\ELECTRONIC\2015\Projects\32. Mas Automated mp3 playing system\PC interface\BackUp\V15.1.5.4\MP3 Scheduler\Backup\MP3 Scheduler\New Event.Designer.vb">
</Event><Event ErrorLevel="0" Project="MP3 Scheduler" Source="MP3 Scheduler\New Event.vb" Description="File successfully backed up as F:\ELECTRONIC\2015\Projects\32. Mas Automated mp3 playing system\PC interface\BackUp\V15.1.5.4\MP3 Scheduler\Backup\MP3 Scheduler\New Event.vb">
</Event><Event ErrorLevel="0" Project="MP3 Scheduler" Source="MP3 Scheduler\AudioFile.vb" Description="File successfully backed up as F:\ELECTRONIC\2015\Projects\32. Mas Automated mp3 playing system\PC interface\BackUp\V15.1.5.4\MP3 Scheduler\Backup\MP3 Scheduler\AudioFile.vb">
</Event><Event ErrorLevel="0" Project="MP3 Scheduler" Source="MP3 Scheduler\Edit Event.Designer.vb" Description="File successfully backed up as F:\ELECTRONIC\2015\Projects\32. Mas Automated mp3 playing system\PC interface\BackUp\V15.1.5.4\MP3 Scheduler\Backup\MP3 Scheduler\Edit Event.Designer.vb">
</Event><Event ErrorLevel="0" Project="MP3 Scheduler" Source="MP3 Scheduler\Edit Event.vb" Description="File successfully backed up as F:\ELECTRONIC\2015\Projects\32. Mas Automated mp3 playing system\PC interface\BackUp\V15.1.5.4\MP3 Scheduler\Backup\MP3 Scheduler\Edit Event.vb">
</Event><Event ErrorLevel="0" Project="MP3 Scheduler" Source="MP3 Scheduler\Form1.vb" Description="File successfully backed up as F:\ELECTRONIC\2015\Projects\32. Mas Automated mp3 playing system\PC interface\BackUp\V15.1.5.4\MP3 Scheduler\Backup\MP3 Scheduler\Form1.vb">
</Event><Event ErrorLevel="0" Project="MP3 Scheduler" Source="MP3 Scheduler\Form1.Designer.vb" Description="File successfully backed up as F:\ELECTRONIC\2015\Projects\32. Mas Automated mp3 playing system\PC interface\BackUp\V15.1.5.4\MP3 Scheduler\Backup\MP3 Scheduler\Form1.Designer.vb">
</Event><Event ErrorLevel="0" Project="MP3 Scheduler" Source="MP3 Scheduler\My Project\AssemblyInfo.vb" Description="File successfully backed up as F:\ELECTRONIC\2015\Projects\32. Mas Automated mp3 playing system\PC interface\BackUp\V15.1.5.4\MP3 Scheduler\Backup\MP3 Scheduler\My Project\AssemblyInfo.vb">
</Event><Event ErrorLevel="0" Project="MP3 Scheduler" Source="MP3 Scheduler\My Project\Application.Designer.vb" Description="File successfully backed up as F:\ELECTRONIC\2015\Projects\32. Mas Automated mp3 playing system\PC interface\BackUp\V15.1.5.4\MP3 Scheduler\Backup\MP3 Scheduler\My Project\Application.Designer.vb">
</Event><Event ErrorLevel="0" Project="MP3 Scheduler" Source="MP3 Scheduler\My Project\Resources.Designer.vb" Description="File successfully backed up as F:\ELECTRONIC\2015\Projects\32. Mas Automated mp3 playing system\PC interface\BackUp\V15.1.5.4\MP3 Scheduler\Backup\MP3 Scheduler\My Project\Resources.Designer.vb">
</Event><Event ErrorLevel="0" Project="MP3 Scheduler" Source="MP3 Scheduler\My Project\Settings.Designer.vb" Description="File successfully backed up as F:\ELECTRONIC\2015\Projects\32. Mas Automated mp3 playing system\PC interface\BackUp\V15.1.5.4\MP3 Scheduler\Backup\MP3 Scheduler\My Project\Settings.Designer.vb">
</Event><Event ErrorLevel="0" Project="MP3 Scheduler" Source="MP3 Scheduler\PlayList.Designer.vb" Description="File successfully backed up as F:\ELECTRONIC\2015\Projects\32. Mas Automated mp3 playing system\PC interface\BackUp\V15.1.5.4\MP3 Scheduler\Backup\MP3 Scheduler\PlayList.Designer.vb">
</Event><Event ErrorLevel="0" Project="MP3 Scheduler" Source="MP3 Scheduler\PlayList.vb" Description="File successfully backed up as F:\ELECTRONIC\2015\Projects\32. Mas Automated mp3 playing system\PC interface\BackUp\V15.1.5.4\MP3 Scheduler\Backup\MP3 Scheduler\PlayList.vb">
</Event><Event ErrorLevel="0" Project="MP3 Scheduler" Source="MP3 Scheduler\My Project\Application.myapp" Description="File successfully backed up as F:\ELECTRONIC\2015\Projects\32. Mas Automated mp3 playing system\PC interface\BackUp\V15.1.5.4\MP3 Scheduler\Backup\MP3 Scheduler\My Project\Application.myapp">
</Event><Event ErrorLevel="0" Project="MP3 Scheduler" Source="MP3 Scheduler\My Project\Settings.settings" Description="File successfully backed up as F:\ELECTRONIC\2015\Projects\32. Mas Automated mp3 playing system\PC interface\BackUp\V15.1.5.4\MP3 Scheduler\Backup\MP3 Scheduler\My Project\Settings.settings">
</Event><Event ErrorLevel="0" Project="MP3 Scheduler" Source="MP3 Scheduler\Resources\Maxmaa logo 3.jpg" Description="File successfully backed up as F:\ELECTRONIC\2015\Projects\32. Mas Automated mp3 playing system\PC interface\BackUp\V15.1.5.4\MP3 Scheduler\Backup\MP3 Scheduler\Resources\Maxmaa logo 3.jpg">
</Event><Event ErrorLevel="0" Project="MP3 Scheduler" Source="MP3 Scheduler\New Event.resx" Description="File successfully backed up as F:\ELECTRONIC\2015\Projects\32. Mas Automated mp3 playing system\PC interface\BackUp\V15.1.5.4\MP3 Scheduler\Backup\MP3 Scheduler\New Event.resx">
</Event><Event ErrorLevel="0" Project="MP3 Scheduler" Source="MP3 Scheduler\Edit Event.resx" Description="File successfully backed up as F:\ELECTRONIC\2015\Projects\32. Mas Automated mp3 playing system\PC interface\BackUp\V15.1.5.4\MP3 Scheduler\Backup\MP3 Scheduler\Edit Event.resx">
</Event><Event ErrorLevel="0" Project="MP3 Scheduler" Source="MP3 Scheduler\Form1.resx" Description="File successfully backed up as F:\ELECTRONIC\2015\Projects\32. Mas Automated mp3 playing system\PC interface\BackUp\V15.1.5.4\MP3 Scheduler\Backup\MP3 Scheduler\Form1.resx">
</Event><Event ErrorLevel="0" Project="MP3 Scheduler" Source="MP3 Scheduler\My Project\Resources.resx" Description="File successfully backed up as F:\ELECTRONIC\2015\Projects\32. Mas Automated mp3 playing system\PC interface\BackUp\V15.1.5.4\MP3 Scheduler\Backup\MP3 Scheduler\My Project\Resources.resx">
</Event><Event ErrorLevel="0" Project="MP3 Scheduler" Source="MP3 Scheduler\PlayList.resx" Description="File successfully backed up as F:\ELECTRONIC\2015\Projects\32. Mas Automated mp3 playing system\PC interface\BackUp\V15.1.5.4\MP3 Scheduler\Backup\MP3 Scheduler\PlayList.resx">
</Event><Event ErrorLevel="0" Project="MP3 Scheduler" Source="MP3 Scheduler\MP3 Scheduler.vbproj" Description="Project converted successfully">
</Event><Event ErrorLevel="3" Project="MP3 Scheduler" Source="MP3 Scheduler\MP3 Scheduler.vbproj" Description="Converted">
</Event><Event ErrorLevel="0" Project="" Source="MP3 Scheduler.sln" Description="Solution converted successfully">
</Event><Event ErrorLevel="3" Project="" Source="MP3 Scheduler.sln" Description="Converted">
</Event><Event ErrorLevel="0" Project="MP3 Scheduler" Source="MP3 Scheduler\MP3 Scheduler.vbproj" Description="Scan complete: Upgrade not required for project files.">
</Event></UpgradeLog>